ccf_openapi_client/__init__.py
ccf_openapi_client/api_client.py
ccf_openapi_client/configuration.py
ccf_openapi_client/exceptions.py
ccf_openapi_client/rest.py
ccf_openapi_client/schemas.py
ccf_openapi_client/apis/__init__.py
ccf_openapi_client/apis/path_to_api.py
ccf_openapi_client/apis/tag_to_api.py
ccf_openapi_client/apis/paths/__init__.py
ccf_openapi_client/apis/paths/aggregate_results.py
ccf_openapi_client/apis/paths/biomarker_term_occurences.py
ccf_openapi_client/apis/paths/biomarker_tree_model.py
ccf_openapi_client/apis/paths/cell_type_term_occurences.py
ccf_openapi_client/apis/paths/cell_type_tree_model.py
ccf_openapi_client/apis/paths/db_status.py
ccf_openapi_client/apis/paths/get_spatial_placement.py
ccf_openapi_client/apis/paths/gtex_rui_locations_jsonld.py
ccf_openapi_client/apis/paths/hubmap_rui_locations_jsonld.py
ccf_openapi_client/apis/paths/ontology_term_occurences.py
ccf_openapi_client/apis/paths/ontology_tree_model.py
ccf_openapi_client/apis/paths/provider_names.py
ccf_openapi_client/apis/paths/reference_organ_scene.py
ccf_openapi_client/apis/paths/reference_organs.py
ccf_openapi_client/apis/paths/scene.py
ccf_openapi_client/apis/paths/sennet_rui_locations_jsonld.py
ccf_openapi_client/apis/paths/sparql.py
ccf_openapi_client/apis/paths/technology_names.py
ccf_openapi_client/apis/paths/tissue_blocks.py
ccf_openapi_client/apis/tags/__init__.py
ccf_openapi_client/apis/tags/default_api.py
ccf_openapi_client/model/__init__.py
ccf_openapi_client/model/aggregate_count.py
ccf_openapi_client/model/database_status.py
ccf_openapi_client/model/error_message.py
ccf_openapi_client/model/flat_spatial_placement.py
ccf_openapi_client/model/get_spatial_placement_request.py
ccf_openapi_client/model/json_ld_object.py
ccf_openapi_client/model/min_max.py
ccf_openapi_client/model/ontology_tree.py
ccf_openapi_client/model/ontology_tree_node.py
ccf_openapi_client/model/rgba.py
ccf_openapi_client/model/sparql_query_request.py
ccf_openapi_client/model/spatial_entity.py
ccf_openapi-1.2.0.dist-info/METADATA
ccf_openapi-1.2.0.dist-info/WHEEL
ccf_openapi-1.2.0.dist-info/top_level.txt
ccf_openapi-1.2.0.dist-info/RECORD
